setup.py
telepot/__init__.py
telepot/api.py
telepot/delegate.py
telepot/exception.py
telepot/filtering.py
telepot/hack.py
telepot/helper.py
telepot/loop.py
telepot/namedtuple.py
telepot/routing.py
telepot.egg-info/PKG-INFO
telepot.egg-info/SOURCES.txt
telepot.egg-info/dependency_links.txt
telepot.egg-info/requires.txt
telepot.egg-info/top_level.txt
telepot/aio/__init__.py
telepot/aio/api.py
telepot/aio/delegate.py
telepot/aio/hack.py
telepot/aio/helper.py
telepot/aio/loop.py
telepot/aio/routing.py
test/test27_admin.py
test/test27_inline.py
test/test27_pay.py
test/test27_queue.py
test/test27_routing.py
test/test27_send.py
test/test27_sticker.py
test/test27_updates.py
test/test3_admin.py
test/test3_inline.py
test/test3_pay.py
test/test3_queue.py
test/test3_routing.py
test/test3_send.py
test/test3_sticker.py
test/test3_updates.py
test/test3a_admin.py
test/test3a_inline.py
test/test3a_pay.py
test/test3a_queue.py
test/test3a_routing.py
test/test3a_send_updates.py
test/test3a_sticker.py